tool.py
whtlib/__init__.py
whtlib/whtlibone.py
whtlib-1.0.0.dist-info/LICENSE.txt
whtlib-1.0.0.dist-info/METADATA
whtlib-1.0.0.dist-info/WHEEL
whtlib-1.0.0.dist-info/top_level.txt
whtlib-1.0.0.dist-info/RECORD
